ormstorm/__init__.py
ormstorm/orm/__init__.py
ormstorm/orm/column.py
ormstorm/orm/constants.py
ormstorm/orm/exceptions.py
ormstorm/orm/table.py
ormstorm/orm/filters/__init__.py
ormstorm/orm/filters/magic.py
ormstorm/utils/__init__.py
ormstorm/utils/dict_factory.py
ormstorm-0.0.3.0.dist-info/LICENSE.txt
ormstorm-0.0.3.0.dist-info/METADATA
ormstorm-0.0.3.0.dist-info/WHEEL
ormstorm-0.0.3.0.dist-info/top_level.txt
ormstorm-0.0.3.0.dist-info/RECORD
