Metadata-Version: 2.1
Name: ormstorm
Version: 0.0.3.0
Summary: Small library for easy work with databases.
Author: Molchaliv
Author-email: molchaliv666@gmail.com
Keywords: python,orm,database,sql,sqlite3
Classifier: Development Status :: 1 - Planning
Classifier: Intended Audience :: Developers
Classifier: Programming Language :: Python :: 3
Classifier: Operating System :: Unix
Classifier: Operating System :: MacOS :: MacOS X
Classifier: Operating System :: Microsoft :: Windows
License-File: LICENSE.txt
